MANIFEST.in
README.rst
setup.py
django_facebook_auth.egg-info/PKG-INFO
django_facebook_auth.egg-info/SOURCES.txt
django_facebook_auth.egg-info/dependency_links.txt
django_facebook_auth.egg-info/requires.txt
django_facebook_auth.egg-info/top_level.txt
facebook_auth/__init__.py
facebook_auth/admin.py
facebook_auth/backends.py
facebook_auth/decorators.py
facebook_auth/forms.py
facebook_auth/models.py
facebook_auth/tests.py
facebook_auth/urls.py
facebook_auth/utils.py
facebook_auth/views.py
facebook_auth/facepy_wrapper/__init__.py
facebook_auth/facepy_wrapper/graph_api.py
facebook_auth/facepy_wrapper/utils.py
facebook_auth/management/__init__.py
facebook_auth/management/commands/__init__.py
facebook_auth/management/commands/debug_user_tokens.py
facebook_auth/migrations/0001_initial.py
facebook_auth/migrations/__init__.py
facebook_auth/south_migrations/0001_initial.py
facebook_auth/south_migrations/0002_auto.py
facebook_auth/south_migrations/0003_auto__add_field_facebookuser_access_token_expiration_date.py
facebook_auth/south_migrations/0004_auto__add_usertoken.py
facebook_auth/south_migrations/0005_move_access_tokens.py
facebook_auth/south_migrations/0006_auto__del_field_facebookuser_access_token__del_field_facebookuser_acce.py
facebook_auth/south_migrations/0007_auto__add_field_facebookuser_scope.py
facebook_auth/south_migrations/0008_remove_duplicate_tokens.py
facebook_auth/south_migrations/0009_auto__add_unique_usertoken_token.py
facebook_auth/south_migrations/0010_auto__chg_field_usertoken_expiration_date__add_unique_usertoken_token.py
facebook_auth/south_migrations/0011_auto__add_field_usertoken_granted_at.py
facebook_auth/south_migrations/0012_auto__chg_field_usertoken_expiration_date.py
facebook_auth/south_migrations/__init__.py