Metadata-Version: 1.0
Name: django-facebook-auth
Version: 3.8.1
Summary: Authorisation app for Facebook API.
Home-page: UNKNOWN
Author: Tomasz Wysocki
Author-email: tomasz@wysocki.info
License: UNKNOWN
Platform: UNKNOWN
